{"name":"searching_by_keyword_apple_should_display_the_corresponding_article","id":"org.example.features.search.SearchByKeywordStory:searching_by_keyword_apple_should_display_the_corresponding_article","testCaseName":"org.example.features.search.SearchByKeywordStory","testSteps":[{"number":1,"description":"Is the home page","duration":5902,"startTime":"2025-04-25T20:00:01.325969300+03:00[Europe/Athens]","screenshots":[{"screenshot":"b29fadacaa21171beab6a8ee60fd2c76334ce65b3fde47e6d085bb2e704d1b8e.png","timeStamp":1745600407228}],"result":"SUCCESS","precondition":false,"level":0},{"number":2,"description":"Looks for: apple","duration":2181,"startTime":"2025-04-25T20:00:07.236043900+03:00[Europe/Athens]","screenshots":[{"screenshot":"24b7aa963803bd746f7c707b9e8ac2194fda5b95d95d4cc7489ae0196fa85763.png","timeStamp":1745600409417}],"result":"SUCCESS","precondition":false,"level":0,"children":[{"number":3,"description":"Enters: apple","duration":2168,"startTime":"2025-04-25T20:00:07.241056+03:00[Europe/Athens]","screenshots":[{"screenshot":"24b7aa963803bd746f7c707b9e8ac2194fda5b95d95d4cc7489ae0196fa85763.png","timeStamp":1745600409408}],"result":"SUCCESS","precondition":false,"level":1},{"number":4,"description":"Starts search","duration":5,"startTime":"2025-04-25T20:00:09.410476800+03:00[Europe/Athens]","screenshots":[{"screenshot":"24b7aa963803bd746f7c707b9e8ac2194fda5b95d95d4cc7489ae0196fa85763.png","timeStamp":1745600409413},{"screenshot":"24b7aa963803bd746f7c707b9e8ac2194fda5b95d95d4cc7489ae0196fa85763.png","timeStamp":1745600409415}],"result":"SUCCESS","precondition":false,"level":1}]},{"number":5,"description":"Should see definition: Rachel Appleby: Observations \u0026 Reflections: Learning from each other, learning from yourself","duration":438,"startTime":"2025-04-25T20:00:09.418990900+03:00[Europe/Athens]","screenshots":[{"screenshot":"24b7aa963803bd746f7c707b9e8ac2194fda5b95d95d4cc7489ae0196fa85763.png","timeStamp":1745600409857}],"result":"SUCCESS","precondition":false,"level":0}],"userStory":{"id":"org.example.features.search.SearchByKeywordStory","storyName":"Search by keyword story","storyClassName":"org.example.features.search.SearchByKeywordStory","path":"search","type":"story"},"featureTag":{"name":"Search/Search by keyword story","type":"story","displayName":"Search/Search by keyword story"},"title":"Searching by keyword apple should display the corresponding article","coreIssues":["#WIKI-1"],"tags":[{"name":"Search","type":"feature","displayName":"Search"},{"name":"Search/Search by keyword story","type":"story","displayName":"Search by keyword story"},{"name":"Search","type":"capability","displayName":"Search for definitions"}],"startTime":"2025-04-25T20:00:00.887877200+03:00[Europe/Athens]","duration":8972,"projectKey":"","sessionId":"852d709b40f630f85d70a2822d1267bb","driver":"chrome","isManualTestingUpToDate":false,"manual":false,"testSource":"JUnit","order":0,"result":"SUCCESS","issues":["#WIKI-1"]}